tests/__init__.py
tests/test_client.py
tgrab/__init__.py
tgrab/__main__.py
tgrab/cli.py
tgrab/client.py
tgrab/dedup.py
tgrab/interactive.py
tgrab/scheduler.py
gibgram-0.1.5.dist-info/METADATA
gibgram-0.1.5.dist-info/WHEEL
gibgram-0.1.5.dist-info/entry_points.txt
gibgram-0.1.5.dist-info/top_level.txt
gibgram-0.1.5.dist-info/RECORD
