Metadata-Version: 2.4
Name: gibgram
Version: 0.1.5
Summary: GibGram: A powerful tool for downloading media from Telegram
Home-page: https://github.com/mosaddiX/gibgram
Author: Hazrat Mosaddique Ali
Author-email: mosaddiqx@gmail.com
Project-URL: Bug Reports, https://github.com/mosaddiX/gibgram/issues
Project-URL: Source, https://github.com/mosaddiX/gibgram
Project-URL: Documentation, https://mosaddix.github.io/gibgram/
Keywords: gibgram,telegram,media,download,cli,bot
Classifier: Development Status :: 4 - Beta
Classifier: Intended Audience :: End Users/Desktop
Classifier: License :: OSI Approved :: MIT License
Classifier: Programming Language :: Python :: 3
Classifier: Programming Language :: Python :: 3.8
Classifier: Programming Language :: Python :: 3.9
Classifier: Programming Language :: Python :: 3.10
Classifier: Programming Language :: Python :: 3.11
Classifier: Programming Language :: Python :: 3.12
Classifier: Topic :: Communications :: Chat
Classifier: Topic :: Utilities
Requires-Python: >=3.8
Requires-Dist: telethon<2.0.0,>=1.28.0
Requires-Dist: cryptg<1.0.0,>=0.4.0
Requires-Dist: rich<14.0.0,>=13.0.0
Requires-Dist: python-dotenv<2.0.0,>=1.0.0
Requires-Dist: pillow<11.0.0,>=10.0.0
Requires-Dist: aiohttp<4.0.0,>=3.8.0
Requires-Dist: aiofiles<24.0.0,>=23.0.0
Provides-Extra: dev
Requires-Dist: pytest<8.0.0,>=7.0.0; extra == "dev"
Requires-Dist: pytest-asyncio<0.22.0,>=0.21.0; extra == "dev"
Requires-Dist: black<24.0.0,>=23.0.0; extra == "dev"
Requires-Dist: isort<6.0.0,>=5.12.0; extra == "dev"
Requires-Dist: flake8<7.0.0,>=6.0.0; extra == "dev"
Requires-Dist: mypy<2.0.0,>=1.0.0; extra == "dev"
Dynamic: author
Dynamic: author-email
Dynamic: classifier
Dynamic: description
Dynamic: description-content-type
Dynamic: home-page
Dynamic: keywords
Dynamic: project-url
Dynamic: provides-extra
Dynamic: requires-dist
Dynamic: requires-python
Dynamic: summary
